{
  "parent": "minecraft:recipes/root",
  "criteria": {
    "has_anvil": {
      "conditions": {
        "items": [
          {
            "items": "minecraft:anvil"
          }
        ]
      },
      "trigger": "minecraft:inventory_changed"
    },
    "has_markers": {
      "conditions": {
        "items": [
          {
            "items": "#quarryplus:markers"
          }
        ]
      },
      "trigger": "minecraft:inventory_changed"
    },
    "has_obsidians": {
      "conditions": {
        "items": [
          {
            "items": "#c:obsidians"
          }
        ]
      },
      "trigger": "minecraft:inventory_changed"
    },
    "has_the_recipe": {
      "conditions": {
        "recipe": "quarryplus:mover"
      },
      "trigger": "minecraft:recipe_unlocked"
    }
  },
  "requirements": [
    [
      "has_the_recipe",
      "has_anvil",
      "has_markers",
      "has_obsidians"
    ]
  ],
  "rewards": {
    "recipes": [
      "quarryplus:mover"
    ]
  }
}