{
  "type": "quarryplus:workbench_recipe",
  "id": "quarryplus:builtin_pump_plus",
  "ingredients": [
    {
      "tag": "forge:ingots/gold",
      "count": 16
    },
    {
      "tag": "forge:ingots/iron",
      "count": 48
    },
    {
      "tag": "forge:dusts/redstone",
      "count": 64
    },
    {
      "tag": "forge:glass/colorless",
      "count": 512
    },
    {
      "item": "minecraft:cactus",
      "count": 80
    }
  ],
  "energy": 320000.0,
  "showInJEI": true,
  "result": {
    "item": "quarryplus:pumpplus",
    "count": 1
  },
  "conditions": [
    {
      "value": "PumpPlus",
      "type": "quarryplus:machine_enabled"
    }
  ]
}
